resolvref/__init__.py
resolvref/exceptions.py
resolvref/expand.py
resolvref/formats.py
resolvref/main.py
resolvref/version.py
resolvref-0.0.3.dist-info/COPYING
resolvref-0.0.3.dist-info/LICENSE
resolvref-0.0.3.dist-info/METADATA
resolvref-0.0.3.dist-info/WHEEL
resolvref-0.0.3.dist-info/entry_points.txt
resolvref-0.0.3.dist-info/top_level.txt
resolvref-0.0.3.dist-info/RECORD
